pyproject_local_kernel/__init__.py
pyproject_local_kernel/__main__.py
pyproject_local_kernel/_configdata.py
pyproject_local_kernel/_identify.py
pyproject_local_kernel/main.py
pyproject_local_kernel/provisioner.py
pyproject_local_kernel/py.typed
pyproject_local_kernel-0.12.1.data/data/share/jupyter/kernels/pyproject_local_kernel/kernel.json
pyproject_local_kernel-0.12.1.data/data/share/jupyter/kernels/pyproject_local_kernel_use_venv/kernel.json
pyproject_local_kernel-0.12.1.dist-info/METADATA
pyproject_local_kernel-0.12.1.dist-info/WHEEL
pyproject_local_kernel-0.12.1.dist-info/entry_points.txt
pyproject_local_kernel-0.12.1.dist-info/licenses/LICENSE.md
pyproject_local_kernel-0.12.1.dist-info/RECORD
