Metadata-Version: 2.3
Name: pyproject-local-kernel
Version: 0.12.1
Summary: Python Jupyter kernel using project/environment manangers like Rye, Uv, PDM, Poetry, Hatch etc.
Project-URL: Homepage, https://bluss.github.io/pyproject-local-kernel/
Project-URL: Repository, https://github.com/bluss/pyproject-local-kernel
Author-email: Ulrik Sverdrup <ulrik.sverdrup@gmail.com>
License: # LICENSE
License-File: LICENSE.md
Keywords: Interactive,Interpreter,Jupyter,Pyproject
Classifier: Framework :: Jupyter
Classifier: Intended Audience :: Developers
Classifier: Intended Audience :: Science/Research
Classifier: Intended Audience :: System Administrators
Classifier: License :: OSI Approved :: MIT License
Classifier: Operating System :: OS Independent
Classifier: Programming Language :: Python
Classifier: Programming Language :: Python :: 3
Classifier: Programming Language :: Python :: 3.8
Classifier: Programming Language :: Python :: 3.9
Classifier: Programming Language :: Python :: 3.10
Classifier: Programming Language :: Python :: 3.11
Classifier: Programming Language :: Python :: 3.12
Classifier: Programming Language :: Python :: 3.13
Requires-Python: >=3.8
Requires-Dist: jupyter-client>=8.6.3
Requires-Dist: tomli>=2.0.1; python_version < '3.11'
Requires-Dist: traitlets>=5.14.3
